napari_labelling_assistant/__init__.py
napari_labelling_assistant/_dock_widget.py
napari_labelling_assistant/_tests/__init__.py
napari_labelling_assistant/_tests/test_dock_widget.py
napari_labelling_assistant-0.0.5.dist-info/LICENSE
napari_labelling_assistant-0.0.5.dist-info/METADATA
napari_labelling_assistant-0.0.5.dist-info/WHEEL
napari_labelling_assistant-0.0.5.dist-info/entry_points.txt
napari_labelling_assistant-0.0.5.dist-info/top_level.txt
napari_labelling_assistant-0.0.5.dist-info/RECORD
