Metadata-Version: 2.1
Name: napari-labelling-assistant
Version: 0.0.5
Summary: A lightweight plugin for visualizing labelling statistics.
Home-page: https://github.com/pranjaldhole/napari-labelling-assistant
Author: Pranjal Dhole
Author-email: dhole.pranjal@gmail.com
License: MIT
Project-URL: Bug Tracker, https://github.com/pranjaldhole/napari-labelling-assistant/issues
Project-URL: Documentation, https://github.com/pranjaldhole/napari-labelling-assistant#README.md
Project-URL: Source Code, https://github.com/pranjaldhole/napari-labelling-assistant
Project-URL: User Support, https://github.com/pranjaldhole/napari-labelling-assistant/issues
Platform: UNKNOWN
Classifier: Development Status :: 2 - Pre-Alpha
Classifier: Intended Audience :: Developers
Classifier: Framework :: napari
Classifier: Topic :: Software Development :: Testing
Classifier: Programming Language :: Python
Classifier: Programming Language :: Python :: 3
Classifier: Programming Language :: Python :: 3.7
Classifier: Programming Language :: Python :: 3.8
Classifier: Programming Language :: Python :: 3.9
Classifier: Operating System :: OS Independent
Classifier: License :: OSI Approved :: MIT License
Requires-Python: >=3.7
License-File: LICENSE
Requires-Dist: napari-plugin-engine (>=0.1.4)
Requires-Dist: numpy
Requires-Dist: matplotlib
